Lab2/DisplayState.v
module DisplayState(state, HEX0, HEX1, HEX2, HEX3, HEX4, HEX5);
	input [3:0] state;
    output reg [6:0] HEX0, HEX1, HEX2, HEX3, HEX4, HEX5;
    
	parameter boat = 7'b1111110;
	parameter wall_in = 7'b1001111;
	parameter wall_in_boat = 7'b1001110;
	parameter wall_out = 7'b1111001;
	parameter wall_out_boat = 7'b1111000;
	parameter empty = 7'b1111111;
	
	always @(state)
		begin
		// 1. 88|88|88
		// 2. -8|88|88 
		// 3. 8-|88|88
		// 4. 88 -8|88
		// 5. 88|-8|88
		// 6. 88|8-|88
		// 7. 88|88 -8
		// 8. 88|88|-8
		// 9. 88|88|8-
			case(state)
				'd0: begin
					HEX5 <= empty;
					HEX4 <= empty;
					HEX3 <= wall_in;
					HEX2 <= wall_out;
					HEX1 <= empty;
					HEX0 <= empty;
				end
				'd1: begin
					HEX5 <= boat;
					HEX4 <= empty;
					HEX3 <= wall_in;
					HEX2 <= wall_out;
					HEX1 <= empty;
					HEX0 <= empty;
				end
				'd2: begin
					HEX5 <= empty;
					HEX4 <= boat;
					HEX3 <= wall_in;
					HEX2 <= wall_out;
					HEX1 <= empty;
					HEX0 <= empty;
				end
				'd3: begin
					HEX5 <= empty;
					HEX4 <= empty;
					HEX3 <= boat;
					HEX2 <= wall_out;
					HEX1 <= empty;
					HEX0 <= empty;
				end
				'd4: begin
					HEX5 <= empty;
					HEX4 <= empty;
					HEX3 <= wall_in_boat;
					HEX2 <= wall_out;
					HEX1 <= empty;
					HEX0 <= empty;
				end
				'd5: begin
					HEX5 <= empty;
					HEX4 <= empty;
					HEX3 <= wall_in;
					HEX2 <= wall_out_boat;
					HEX1 <= empty;
					HEX0 <= empty;
				end
				'd6: begin
					HEX5 <= empty;
					HEX4 <= empty;
					HEX3 <= wall_in;
					HEX2 <= empty;
					HEX1 <= boat;
					HEX0 <= empty;
				end
				'd7: begin
					HEX5 <= empty;
					HEX4 <= empty;
					HEX3 <= wall_in;
					HEX2 <= wall_out;
					HEX1 <= boat;
					HEX0 <= empty;
				end
				'd8: begin
					HEX5 <= empty;
					HEX4 <= empty;
					HEX3 <= wall_in;
					HEX2 <= wall_out;
					HEX1 <= empty;
					HEX0 <= boat;
				end
				'd9: begin
					HEX5 <= empty;
					HEX4 <= boat;
					HEX3 <= empty;
					HEX2 <= wall_out;
					HEX1 <= empty;
					HEX0 <= empty;
				end
				'd10: begin
					HEX5 <= empty;
					HEX4 <= empty;
					HEX3 <= wall_in;
					HEX2 <= boat;
					HEX1 <= empty;
					HEX0 <= empty;
				end
				default: begin
					HEX5 <= empty;
					HEX4 <= empty;
					HEX3 <= wall_in;
					HEX2 <= wall_out;
					HEX1 <= empty;
					HEX0 <= empty;
				end
			endcase
		
		end

endmodule

Lab2/LockSystem.v
module TopLevelLockSystem
		#( parameter INNER = 5*560,  parameter OUTER = 0, parameter TOLERANCE = 0.3*560)
		(/* Inputs */ clk, reset, inner_door_sw, outer_door_sw, outer_gondola_arrival_sw, inner_gondola_arrival_sw, inc_water_level, dec_water_level,
		/* Outputs */ inner_gondola_led, outer_gondola_led, outer_door_openable_led, inner_door_openable_led,
		/* Display */ HEX0, HEX1, HEX2, HEX3, HEX4, HEX5);
		
	input clk, reset, inner_door_sw, outer_door_sw, outer_gondola_arrival_sw, inner_gondola_arrival_sw, inc_water_level, dec_water_level;
	output inner_gondola_led, outer_gondola_led, outer_door_openable_led, inner_door_openable_led;
	output wire [6:0] HEX0, HEX1, HEX2, HEX3, HEX4, HEX5;
	
	// State
	reg rst, empty;
	wire [3:0] state;
	
	// We need water_level such that we can show the 0.3 boundary
	wire [16:0] water_level;
	
	WaterSystem waterSystem (inc_water_level, dec_water_level, clk, reset, water_level, outer_door_openable_led, inner_door_openable_led);
	GondolaDoorLight gondolaDoorLight (inner_door_sw, outer_door_sw, outer_gondola_arrival_sw, inner_gondola_arrival_sw, water_level, reset, clk, inner_gondola_led, outer_gondola_led, state);
	DisplayState displayState (state, HEX0, HEX1, HEX2, HEX3, HEX4, HEX5);

endmodule

/*
The terminology "Arrival SW" or "Arrival LED" and "Departure SW" or "Departure LED"
are direction dependant. If the SW corresponding to outer is pressed, then "Arrival"
side refers to outer, and "Departure" refers to inner.

Lights should change:
1. The "Arrival SW" informs the side the gondola is arriving from,
which turns on the corresponding side's LED
2. The "Arrival LED" can return to LOW iff:
		1. water_level is within the 0.3 margin such that the proper "Arrival" door LED is illuminated
		2. 5 minutes have passed such that the boat is waiting for the door to open
		3. Operator pressed the "Arrival SW" door open switch
3. The "Departure LED" will go HIGH iff:
		1. The boat is in the pound (the procedure in 1 and 2 occurred)
		2. water_level is within the 0.3 margin such that the "Departure" door LED is illuminated
		3. Operator pressed the "Departure SW" door open switch
4. The "Departure LED" will go low after 5 minutes.

LEDs can only cycle from "Arrival" to "Departure" except if the operator pressed the wrong direction key.
*/
module GondolaDoorLight
		#( parameter INNER = 5*560,  parameter OUTER = 0*560, parameter TOLERANCE = 0.3*560, parameter GONDOLA_ARR_DELAY = 5, parameter GONDOLA_DEPT_DELAY = 5)
		(/* Inputs */ inner_door_sw, outer_door_sw, outer_gondola_arrival_sw, inner_gondola_arrival_sw, water_level, reset, clk,
		/* Outputs */ inner_gondola_led, outer_gondola_led, state);
		
		// Clock and reset input
		input clk, reset;
		// Door controls
		input inner_door_sw, outer_door_sw;
		// Gondola arrival controls
		input outer_gondola_arrival_sw, inner_gondola_arrival_sw;
		// Gondola LED output
		output inner_gondola_led, outer_gondola_led;
		reg inner_gondola_led, outer_gondola_led;
		// Needed to respond to inner_door_sw and outer_door_sw
		input [16:0] water_level;
		
		// Display state
		output reg [3:0] state;
		
		// Can change arrival switch only after 5
		reg [16:0] counter;
		
		// Once the gondola enters the lock, we need to know what direction it needs to go
		// Clear these once the gondolas leave the locks
		// TODO: Should we have position track clear state instead?
		reg to_outer, to_inner;
		
		// 0: arriving, 1: in pound, 2: departing
		// TODO: Should we have position track clear state instead?
		reg [8:0] position;
		
		// We should only keep the counter incrementing until the highest value of the counter we care about
		reg [16:0] counter_max = GONDOLA_ARR_DELAY > GONDOLA_DEPT_DELAY ? GONDOLA_ARR_DELAY : GONDOLA_DEPT_DELAY;
		
		// TODO: Perhaps reduce duplication with the LED in the other module
		assign outer_door_openable = water_level <= OUTER + TOLERANCE;
		assign inner_door_openable = water_level >= INNER - TOLERANCE;
		
		always @ (posedge clk)
			begin
				// We need to mark the canal as clear and reset its state if:
				// 1. The boat is in position 2 (leaving) and the counter is at least GONDOLA_DEPT_DELAY
				// 2. We reset
				if (reset || (position == 2 && counter >= GONDOLA_DEPT_DELAY))
					begin
						// Reset to default values
						// Do not reset water. It is handled by the WaterSystem module.
						counter = 0;
						to_outer = 0;
						to_inner = 0;
						position = 0;
						inner_gondola_led = 0;
						outer_gondola_led = 0;
						state = 'd0;
					end
				else
					begin
						counter = counter < counter_max ? counter + 1 : counter_max;
					end
			end
		
		
		always @ (posedge inner_door_sw)
			begin
				case(position)
				0:
				// Boat is before the pound, only move forward if:
				// 1. It's been long enough (>=GONDOLA_ARR_DELAY)
				// 2. it's going to_outer
				// 3. inner_door_openable is true
					if (inner_door_openable && counter >= GONDOLA_ARR_DELAY && to_outer)
					begin
						position = 1;
						// Both lights on when boat is in the pound
						outer_gondola_led = 1;
						inner_gondola_led = 1;
						state = 'd3;
					end
				1:
				// Boat is in the pound, only move forward if:
				// 2. it's going to_inner
				// 3. inner_door_openable is true
					if (inner_door_openable && to_inner)
					begin
						position = 2;
						outer_gondola_led = 0;
						inner_gondola_led = 1;
						// Restart counter as we need to wait for the boat to leave
						counter = 0;
						state = 'd9;
					end
				endcase
			end
			
		always @ (posedge outer_door_sw)
			begin
				case(position)
				0:
				// Boat is before the pound, only move forward if:
				// 1. It's been long enough (>=GONDOLA_ARR_DELAY)
				// 2. it's going to_inner
				// 3. outer_door_openable is true
					if (outer_door_openable && counter >= GONDOLA_ARR_DELAY && to_inner)
					begin
						position = 1;
						// Both lights on when boat is in the pound
						outer_gondola_led = 1;
						inner_gondola_led = 1;
						state = 'd10;
					end
				1:
				// Boat is in the pound, only move forward if:
				// 2. it's going to_outer
				// 3. outer_door_openable is true
					if (outer_door_openable && to_outer)
					begin
						position = 2;
						// Restart counter as we need to wait for the boat to leave
						counter = 0;
						inner_gondola_led = 0;
						outer_gondola_led = 1;
						state = 'd6;
					end
				endcase
			end
		
		// No gondolas may arrive during the lock traversal procedure
		// Start timer, such that the pound becomes enter-able only after GONDOLA_DEPT_DELAY units after the boat leaves the lock
		always @ (posedge outer_gondola_arrival_sw)
			begin
				// reset must be low, and there needs to be no boats currently traversing (!to_outer && !to_inner)
				if (!reset && !to_outer && !to_inner)
					begin
						counter = 0;
						position = 0;
						to_outer = 0;
						to_inner = 1;
						outer_gondola_led = 1;
						state = 'd8;
					end
			end
				
		always @ (posedge inner_gondola_arrival_sw)
			begin
				// reset must be low, and there needs to be no boats currently traversing (!to_outer && !to_inner)
				if (!reset && !to_outer && !to_inner)
					begin
						counter = 0;
						position = 0;
						to_outer = 1;
						to_inner = 0;
						inner_gondola_led = 1;
						state = 'd1;
					end
			end
		
endmodule


/*
Updates water level at the correct rate.
Stops updating water volume after Open/Close Inner/Outer is triggered.
*/
module WaterSystem
		#( parameter INNER = 5*560,  parameter OUTER = 560*0, parameter TOLERANCE = 560*0.3, parameter INC_AMT = 5 * 560 / 8, parameter DEC_AMT = 5 * 560 / 7)
		(/* Inputs */ inc_water_level, dec_water_level, clk, reset,
		/* Outputs */ water_level, outer_door_openable_led, inner_door_openable_led);
		
		// Water level controls
		input inc_water_level, dec_water_level;
		// Clock and reset input
		input clk, reset;
		
		// water_level changes responding to the WaterSystem
		output [16:0] water_level;
		reg [16:0] water_level;
		
		// Wires for continuous increment (not truly continuous as water increments only at clk boundary)
		output outer_door_openable_led, inner_door_openable_led;
		wire outer_door_openable_led, inner_door_openable_led;
		
		assign outer_door_openable_led = water_level < OUTER + TOLERANCE;
		assign inner_door_openable_led = water_level > INNER - TOLERANCE;
		
		// To hold state of inc_pressed 
		reg inc_pressed, dec_pressed;
		
		always @ (posedge clk)
			begin
			// Increment water level if key was pressed or reset if reset is high
			// Limits rate at which water can increase
				if (reset)
					begin
						// Reset to default values
						// water_level = OUTER;
						// outer_led = HIGH;
						water_level = OUTER;
						inc_pressed = 1'b0;
						dec_pressed = 1'b0;
					end
				else
					// Only respond to inc/dec_water_level if not resetting
					begin
						if (inc_pressed)
							begin
								// Bound the max water level to be INNER
								water_level = water_level + INC_AMT < INNER ? water_level + INC_AMT : INNER;
								inc_pressed = 1'b0;
							end
						if (dec_pressed)
							begin
								// Bound the min water level to be OUTER
								water_level = water_level - DEC_AMT > OUTER ? water_level - DEC_AMT : OUTER;
								dec_pressed = 1'b0;
							end
					end
			end
		
		always @ (posedge inc_water_level)
			inc_pressed = 1'b1;
		always @ (posedge dec_water_level)
			dec_pressed = 1'b1;
		
endmodule

Lab2/Tester.v
`include "LockSystem.v"
`include "DisplayState.v"
module testBench();
	
	// Input
	wire inner_gondola_led, outer_gondola_led, outer_door_openable_led, inner_door_openable_led;
	// Output
	wire clk, reset, inner_door_sw, outer_door_sw, outer_gondola_arrival_sw, inner_gondola_arrival_sw,
			inc_water_level, dec_water_level;
	wire [6:0] HEX0, HEX1, HEX2, HEX3, HEX4, HEX5;
		
	// Declare instance of device under test
	TopLevelLockSystem dut (clk, reset, inner_door_sw, outer_door_sw,
		outer_gondola_arrival_sw, inner_gondola_arrival_sw, inc_water_level, dec_water_level,inner_gondola_led,
		outer_gondola_led, outer_door_openable_led, inner_door_openable_led,
		HEX0, HEX1, HEX2, HEX3, HEX4, HEX5);


	// Declare an instance of the Tester module
	Tester aTester (clk, reset, inner_door_sw, outer_door_sw, outer_gondola_arrival_sw, inner_gondola_arrival_sw,
		 inc_water_level,dec_water_level, inner_gondola_led, outer_gondola_led, outer_door_openable_led, inner_door_openable_led,
		 HEX0, HEX1, HEX2, HEX3, HEX4, HEX5);

	// dumpfile for gtkwave
	initial
	begin
		$dumpfile("LockSystem.vcd");
		$dumpvars(1, dut);
	end
endmodule

module Tester(clk, reset, inner_door_sw, outer_door_sw, outer_gondola_arrival_sw, inner_gondola_arrival_sw,
	 inc_water_level,dec_water_level,inner_gondola_led, outer_gondola_led, outer_door_openable_led,
	 inner_door_openable_led, HEX0, HEX1, HEX2, HEX3, HEX4, HEX5);
	 
		// Output
		
		// Input of Lock System
		output clk, reset, inner_door_sw, outer_door_sw, outer_gondola_arrival_sw, inner_gondola_arrival_sw,
			inc_water_level, dec_water_level;
		// Output of Lock System
		reg clk, reset, inner_door_sw, outer_door_sw, outer_gondola_arrival_sw, inner_gondola_arrival_sw,
			inc_water_level, dec_water_level;
		
		// Output 
		output inner_gondola_led, outer_gondola_led, outer_door_openable_led, inner_door_openable_led;
		wire inner_gondola_led, outer_gondola_led, outer_door_openable_led, inner_door_openable_led;
		
		output wire [6:0] HEX0, HEX1, HEX2, HEX3, HEX4, HEX5;
		
		/*
		// Declare instance of device under test
		TopLevelLockSystem dut (clk, reset, inner_door_sw, outer_door_sw,
			outer_gondola_arrival_sw, inner_gondola_arrival_sw, inc_water_level, dec_water_level,inner_gondola_led,
			outer_gondola_led, outer_door_openable_led, inner_door_openable_led);	
		*/
		
		// Instantiate a logging module
		output reg log = 1;
		output reg [7*8:0] level = "INITIAL";
		Logger logger(log, level, {inner_door_sw, outer_door_sw, outer_gondola_arrival_sw, inner_gondola_arrival_sw,
		  inc_water_level, dec_water_level,inner_gondola_led, outer_gondola_led, outer_door_openable_led,
		  inner_door_openable_led, clk, reset}, {HEX5, HEX4, HEX3, HEX2, HEX1, HEX0} );
		
		// Test vars
		parameter stimDelay = 20;
		parameter nSteps = 64;
		// Decrease these delays to verify specific amounts...
		integer i = 0, j = 0, boat_delay = 10, rise_delay = 8, fall_delay = 7;

		/* Kevin:Leaving this here incase y'all wanna revert
		initial begin 
			$display(" inner_door_sw  |  outer_door_sw |  outer_gondola_arrival_sw  |  inner_gondola_arrival_sw  |  inc_water_level  |  dec_water_level  |  inner_gondola_led  |  outer_gondola_led  |  outer_door_openable_led  |  inner_door_openable_led  |  Clock  |  Reset  |  Time ");
			$monitor(" %b  |  %b  |  %b |  %b  |  %b  |  %b  |  %b  |  %b  |  %b  |  %b  |  %b  |  %b  |  %t",
			inner_door_sw, outer_door_sw, outer_gondola_arrival_sw, inner_gondola_arrival_sw, inc_water_level, dec_water_level, inner_gondola_led,
			outer_gondola_led, outer_door_openable_led, inner_door_openable_led, clk, reset, $time);
		end
        */
		
		initial
		begin
			// Prime the system
			clk = 1'b0;
			reset = 1'b1;
			inner_door_sw = 1'b0;
			outer_door_sw = 1'b0;
			outer_gondola_arrival_sw = 1'b0;
			inner_gondola_arrival_sw = 1'b0;
			inc_water_level = 1'b0;
			dec_water_level = 1'b0;
			#stimDelay clk = 1'b1;
			#stimDelay clk = ~clk;
			reset = 1'b0;

			// Logging pattern
            level = "RESET--"; log = ~log;

			#stimDelay clk = ~clk;
			#stimDelay clk = ~clk;
			#stimDelay clk = ~clk;

			// Signal a Gondola.
			outer_gondola_arrival_sw = 1'b1;
			#stimDelay clk = ~clk;
            level = "SIGNAL-"; log = ~log;
			outer_gondola_arrival_sw = 1'b0;
			#stimDelay clk = ~clk;

			// Wait for gondola to arrive
			// Multiply by 2 since ticks are only on posedge
			for (j = 0; j < boat_delay*2; j=j+1) begin
				#stimDelay clk = ~clk;
			end
			#stimDelay clk = ~clk;
            level = "ARRIVE-"; log = ~log;

			// Open the outer gate.
			outer_door_sw = 1'b1;
			#stimDelay clk = ~clk;
            level = "GATEOPN"; log = ~log;
			outer_door_sw = 1'b0;
			#stimDelay clk = ~clk;


			for (i = 0; i < rise_delay*2; i=i+1) begin
				// Increase water level for awhile
				inc_water_level = 1'b1;
				inc_water_level = 1'b0;
			    #stimDelay clk = ~clk;
			end
			
			// Open the inner gate.
			inner_door_sw = 1'b1;
			#stimDelay clk = ~clk;
			inner_door_sw = 1'b0;
			#stimDelay clk = ~clk;
			
			// Wait for boat to depart
			for (j = 0; j < boat_delay*2; j=j+1) begin
				#stimDelay clk = ~clk;
			end

			// TODO: Start next test...
			for (j = 0; j < boat_delay*2; j=j+1) begin
				#stimDelay clk = ~clk;
			end
			
			// TEST 2: While water is HIGH, Gondola arrives from outer as before, moves through pound, leaves.

			// TEST 3: Gondola arrives from inner. Fiddle around with the water level to look at the LEDs.

			// TEST 4: Gondola signals from outer. Open outer door before it arrives. Open the wrong door to make sure it doesn't go through.

			$finish; // finish simulation
		end
endmodule

module Logger
  #( parameter DUT="TopLevelLockSystem" )
  (
    log, level, dutPort, HEX
  );

  // Toggling log sends a message
  input log;

  // 7 char string to say where the system is at
  input [7*8:0] level;

  // DUT info
  input [11:0] dutPort;
  input [5:0][6:0] HEX;
  
  always @ (posedge log or negedge log) begin
      $display({"%s:@%s  State:", 
        "{inner_door_sw:%b, ", 
        "outer_door_sw:%b, ", 
        "outer_gondola_arrival_sw:%b, ",
        "inner_gondola_arrival_sw:%b, ",
        "inc_water_level:%b, ",
        "dec_water_level:%b, ",
        "inner_gondola_led:%b, ",
        "outer_gondola_led:%b, ",
        "outer_door_openable_led:%b, ",
        "inner_door_openable_led:%b, ",
        "clk:%b, reset:%b, ",
		"HEX5:%b, HEX4:%b, HEX3:%b, HEX2:%b, HEX1:%b, HEX0:%b}", 
		"%t|timestamp"},
        DUT,level,dutPort[11],dutPort[10],dutPort[9],
        dutPort[8],dutPort[7],dutPort[6],dutPort[5],dutPort[4],
		dutPort[3],dutPort[2],dutPort[1],dutPort[0],
		HEX[5],HEX[4],HEX[3],HEX[2],HEX[1],HEX[0],
        $time);
  end

endmodule

Lab2/LockSystem.vcd
$date
	Sun Apr 30 13:25:35 2017
$end
$version
	Icarus Verilog
$end
$timescale
	1s
$end
$scope module testBench $end
$scope module dut $end
$var wire 1 ! clk $end
$var wire 1 " dec_water_level $end
$var wire 1 # inc_water_level $end
$var wire 1 $ inner_door_sw $end
$var wire 1 % inner_gondola_arrival_sw $end
$var wire 1 & outer_door_sw $end
$var wire 1 ' outer_gondola_arrival_sw $end
$var wire 1 ( reset $end
$var wire 17 ) water_level [16:0] $end
$var wire 4 * state [3:0] $end
$var wire 1 + outer_gondola_led $end
$var wire 1 , outer_door_openable_led $end
$var wire 1 - inner_gondola_led $end
$var wire 1 . inner_door_openable_led $end
$var wire 7 / HEX5 [6:0] $end
$var wire 7 0 HEX4 [6:0] $end
$var wire 7 1 HEX3 [6:0] $end
$var wire 7 2 HEX2 [6:0] $end
$var wire 7 3 HEX1 [6:0] $end
$var wire 7 4 HEX0 [6:0] $end
$upscope $end
$upscope $end
$enddefinitions $end
#0
$dumpvars
bx 4
bx 3
bx 2
bx 1
bx 0
bx /
0.
x-
1,
x+
bx *
bx )
1(
0'
0&
0%
0$
0#
0"
0!
$end
#20
b1111111 4
b1111111 3
b1111001 2
b1001111 1
b1111111 0
b1111111 /
b0 )
b0 *
0+
0-
1!
#40
0(
0!
#60
1!
#80
0!
#100
b1111110 4
b1000 *
1+
1'
1!
#120
0'
0!
#140
1!
#160
0!
#180
1!
#200
0!
#220
1!
#240
0!
#260
1!
#280
0!
#300
1!
#320
0!
#340
1!
#360
0!
#380
1!
#400
0!
#420
1!
#440
0!
#460
1!
#480
0!
#500
1!
#520
0!
#540
1!
#560
b1111111 4
b1111110 2
b1010 *
1-
1&
0!
#580
0&
1!
#600
0#
0!
#620
0,
b101011110 )
0#
1!
#640
0#
0!
#660
b1010111100 )
0#
1!
#680
0#
0!
#700
b10000011010 )
0#
1!
#720
0#
0!
#740
b10101111000 )
0#
1!
#760
0#
0!
#780
b11011010110 )
0#
1!
#800
0#
0!
#820
b100000110100 )
0#
1!
#840
0#
0!
#860
b100110010010 )
0#
1!
#880
0#
0!
#900
1.
b101011110000 )
0#
1!
#920
b1111001 2
b1111111 1
b1111110 0
b1001 *
0+
1$
0!
#940
0$
1!
#960
0!
#980
1!
#1000
0!
#1020
1!
#1040
0!
#1060
1!
#1080
0!
#1100
1!
#1120
0!
#1140
b1001111 1
b1111111 0
b0 *
0-
1!
